snakecrypter/__init__.py
snakecrypter/cli.py
snakecrypter/encryptor.py
snake_crypter-0.1.1.dist-info/METADATA
snake_crypter-0.1.1.dist-info/WHEEL
snake_crypter-0.1.1.dist-info/entry_points.txt
snake_crypter-0.1.1.dist-info/top_level.txt
snake_crypter-0.1.1.dist-info/RECORD
