Metadata-Version: 2.1
Name: snake-crypter
Version: 0.1.1
Summary: A Python package to encrypt and run programs using XOR encryption
Author: LNodesL
Author-email: lnodesl@yahoo.com
License: MIT
Keywords: encryption decryption XOR c++ cli c crypter
